 {
	"uninstall-survey-free": {
		"en-US": {
			"enabled": false,
			"probability": 1.0,
			"campaign": "US20170509",
			"url": "https://www.surveymonkey.com/r/english-opened-uninstall"
		},
		"zh-CN": {
			"enabled": false,
			"probability": 1.0,
			"campaign": "US20180427",
			"url": "https://www.surveymonkey.com/r/chinese-free-427"
		}
	},
	"uninstall-survey-pro": {
		"en-US": {
			"enabled": false,
			"probability": 1.0,
			"campaign": "US20170509",
			"url": "https://www.surveymonkey.com/r/english-pro"
		},
		"zh-CN": {
			"enabled": false,
			"probability": 1.0,
			"campaign": "US20180427",
			"url": "https://www.surveymonkey.com/r/chinese-pro-427"
		}
	},
	"survey": {
		"en-CN": {
			"enabled": false,
			"probability": 0.00,
			"campaign": "beta-4.7.14",
			"url": "https://t.me/joinchat/BxT4KUg7B5HATgrFP22VXg",
			"message": "Please join the Lantern beta group to test the latest features!",
			"thanks": "",
			"button": "Join Now!"
		},
		"US": {
			"enabled": false,
			"probability": 0.00,
			"campaign": "US20170405",
			"url": "?utm_source=upgradesnack&utm_campaign=Privateupgrade#/plans",
			"message": "Upgrade to Pro for fast, stable service!",
			"thanks": "",
			"button": "Upgrade!"
		},
		"en": {
			"enabled": false,
			"probability": 0.00,
			"campaign": "20170227",
			"url": "",
			"message": "",
			"thanks": "",
			"button": ""
		},
		"zh-CN": {
			"enabled": true,
			"probability": 1.00,
			"campaign": "20180619",
			"url": "https://yin.bi/?utm_source=lantern&utm_medium=snackbar&utm_campaign=snackbar_ad",
			"message": "隐币：无封锁的加密货币即将到来。",
			"thanks": "",
			"button": "阅读白皮书"

		},
		"IN": {
			"enabled": false,
			"probability": 0.00,
			"campaign": "20180821",
			"url": "https://www.surveymonkey.com/r/JGZ9CD7",
			"message": "Lantern is hiring an engineer in India! For more info, and to apply",
			"thanks": "Thanks for your application!",
			"button": "Click Here"
		},
		"en-IN": {
			"enabled": false,
			"probability": 1.00,
			"campaign": "20170227",
			"url": "https://www.surveymonkey.com/r/JGZ9CD7",
			"message": "Lantern is hiring an engineer in India! For more info, and to apply",
			"thanks": "Thanks for your application!",
			"button": "Click Here"
		}
	}
}
