{
   "defaultLocale":"en-US",
   "ads":{
      "en_US":{
         "enabled":true,
         "text": "隐币-无封锁的加密货币即将到来。\n点击此处了解如何免费获得。"
      },
      "zh_CN":{
         "enabled":true,
         "text": "隐币-无封锁的加密货币即将到来。\n点击此处了解如何免费获得。"
      }
   },
   "surveys":{
      "US":{
         "enabled":false,
         "probability":1.00,
         "campaign":"20160801",
         "url":"https://www.surveymonkey.com/r/WPZG9JZ",
         "message":"Are you using lantern from the USA? Take this short survey!",
         "thanks":"Thanks for taking our survey!",
         "button":"Take survey"
      },
      "en_US":{
         "enabled":false,
         "probability":1.00,
         "userType": "free",
         "showPlansScreen": true,
         "campaign":"20160801",
         "url":"",
         "message":"Try Lantern Pro now for faster, reliable service!",
         "thanks":" ",
         "button":"Upgrade Now"
      },
      "en_GB":{
         "enabled":false,
         "probability":1.00,
         "userType": "free",
         "showPlansScreen": true,
         "campaign":"20160801",
         "url":"",
         "message":"Try Lantern Pro now for faster, reliable service!",
         "thanks":"",
         "button":"Upgrade Now"
      },
      "zh_CN":{
         "enabled":false,
         "probability":1.00,
         "campaign":"20180313",
         "url":"https://www.getlantern.org",
         "message":"点击上方按钮升级到专业版，来享受更快更稳定的服务！",
         "thanks":"",
         "button":"."
      },
      "en_IN":{
         "enabled":false,
         "probability":0.00,
         "campaign":"201700305",
         "url":"https://www.surveymonkey.com/r/JGZ9CD7",
         "message":"Lantern is hiring an engineer in India! For more info, and to apply",
         "thanks":"Thanks for your application!",
         "button":"Click Here"
      },
      "en":{
         "enabled":false,
         "probability":0.00,
         "campaign":"201700305",
         "url":"https://www.surveymonkey.com/r/JGZ9CD7",
         "message":"Lantern is hiring an engineer in India! For more info, and to apply",
         "thanks":"Thanks for your application!",
         "button":"Click Here"
      }
   }
}
